MANIFEST.in
setup.cfg
setup.py
magedock/__init__.py
magedock/cli.py
magedock.egg-info/PKG-INFO
magedock.egg-info/SOURCES.txt
magedock.egg-info/dependency_links.txt
magedock.egg-info/entry_points.txt
magedock.egg-info/not-zip-safe
magedock.egg-info/requires.txt
magedock.egg-info/top_level.txt
magedock/commands/__init__.py
magedock/commands/db.py
magedock/commands/helper.py
magedock/commands/init.py
magedock/commands/ssh.py
magedock/commands/start.py
magedock/commands/stop.py
magedock/templates/docker-compose.yml