Metadata-Version: 1.1
Name: magedock
Version: 0.1.6
Summary: A tool to assist with handling of Magento 2.x projects for development.
Home-page: https://github.com/hardikgajjar/magedock
Author: Hardik Gajjar
Author-email: hardik.kwt@gmail.com
License: BSD
Platform: any
Classifier: Development Status :: 4 - Beta
Classifier: Environment :: Console
Classifier: Intended Audience :: Developers
Classifier: License :: OSI Approved :: BSD License
Classifier: Operating System :: POSIX
Classifier: Operating System :: MacOS
Classifier: Operating System :: Unix
Classifier: Programming Language :: Python
Classifier: Programming Language :: Python :: 2
Classifier: Programming Language :: Python :: 3
Classifier: Topic :: Software Development :: Libraries :: Python Modules
